ccg_django_utils/__init__.py
ccg_django_utils/http.py
ccg_django_utils/loghandlers.py
ccg_django_utils/webhelpers.py
ccg_django_utils/conf.py
ccg_django_utils-0.4.2.dist-info/top_level.txt
ccg_django_utils-0.4.2.dist-info/METADATA
ccg_django_utils-0.4.2.dist-info/DESCRIPTION.rst
ccg_django_utils-0.4.2.dist-info/metadata.json
ccg_django_utils-0.4.2.dist-info/WHEEL
ccg_django_utils-0.4.2.dist-info/RECORD
